Lab2-SigGen/task3/ram2ports.sv
module ram2ports #(
    parameter ADDRESS_WIDTH=9,
              DATA_WIDTH=8
)(

    input logic clk,
    input logic wr_en,
    input logic rd_en,
    input logic [ADDRESS_WIDTH-1:0] wr_addr,
    input logic [ADDRESS_WIDTH-1:0] rd_addr,
    input logic [DATA_WIDTH-1:0] din,
    output logic [DATA_WIDTH-1:0] dout
);


logic [DATA_WIDTH-1:0] ram_array [2**ADDRESS_WIDTH-1:0];

always_ff @(posedge clk) begin
    if (wr_en==1'b1)
        ram_array[wr_addr] <= din;
    if (rd_en ==1'b1)
        dout <= ram_array[rd_addr];

end
endmodule

Lab2-SigGen/task3/counter.sv
module counter #(
  parameter WIDTH = 9
)(
  // interface signals
  input  logic             clk,      // clock 
  input  logic             rst,      // reset 
  input  logic             en,       // enable
  input  logic [WIDTH-1:0] incr,        // value to preload
  output logic [WIDTH-1:0] count     // count output
);

always_ff @ (posedge clk)
  if (rst) count <= {WIDTH{1'b0}};
  else     count <= en ? count + incr  : count;
endmodule

Lab2-SigGen/task3/sigdelay.sv
module sigdelay #(
    parameter A_WIDTH=9,
              D_WIDTH=8
)(
input logic clk, //clk
input logic rst, //reset
input logic en, //enable
input logic wr, //write enable
input logic rd, //read enable
input logic [A_WIDTH-1:0] offset, //offset
input  logic [D_WIDTH:0]  incr, //increment for addr counter
input  logic [D_WIDTH-1:0] mic_signal, //input data
output  logic [D_WIDTH-1:0] delayed_signal //output data
);

logic [A_WIDTH-1:0] address; //interconnect wire

counter addrCounter (
    .clk (clk),
    .rst (rst),
    .en (1),
    .count (address)
);

ram2ports sigRam (
    .clk (clk),
    .rd_en (rd),
    .wr_en (wr),
    .rd_addr (address-offset),
    .wr_addr (address),
    .din (mic_signal),
    .dout (delayed_signal)
);

endmodule

Lab2-SigGen/task3/sigdelay.vcd
$version Generated by VerilatedVcd $end
$timescale 1ps $end

 $scope module TOP $end
  $var wire  1 # clk $end
  $var wire  8 + delayed_signal [7:0] $end
  $var wire  1 % en $end
  $var wire  9 ) incr [8:0] $end
  $var wire  8 * mic_signal [7:0] $end
  $var wire  9 ( offset [8:0] $end
  $var wire  1 ' rd $end
  $var wire  1 $ rst $end
  $var wire  1 & wr $end
  $scope module sigdelay $end
   $var wire 32 . A_WIDTH [31:0] $end
   $var wire 32 / D_WIDTH [31:0] $end
   $var wire  9 , address [8:0] $end
   $var wire  1 # clk $end
   $var wire  8 + delayed_signal [7:0] $end
   $var wire  1 % en $end
   $var wire  9 ) incr [8:0] $end
   $var wire  8 * mic_signal [7:0] $end
   $var wire  9 ( offset [8:0] $end
   $var wire  1 ' rd $end
   $var wire  1 $ rst $end
   $var wire  1 & wr $end
   $scope module addrCounter $end
    $var wire 32 . WIDTH [31:0] $end
    $var wire  1 # clk $end
    $var wire  9 , count [8:0] $end
    $var wire  1 0 en $end
    $var wire  9 1 incr [8:0] $end
    $var wire  1 $ rst $end
   $upscope $end
   $scope module sigRam $end
    $var wire 32 . ADDRESS_WIDTH [31:0] $end
    $var wire 32 / DATA_WIDTH [31:0] $end
    $var wire  1 # clk $end
    $var wire  8 * din [7:0] $end
    $var wire  8 + dout [7:0] $end
    $var wire  9 - rd_addr [8:0] $end
    $var wire  1 ' rd_en $end
    $var wire  9 , wr_addr [8:0] $end
    $var wire  1 & wr_en $end
   $upscope $end
  $upscope $end
 $upscope $end
$enddefinitions $end


#0
1#
0$
0%
1&
1'
b001000000 (
b000000000 )
b00000000 *
b00000000 +
b000000000 ,
b111000000 -
b00000000000000000000000000001001 .
b00000000000000000000000000001000 /
10
b000000000 1
#1
0#
#2
1#
b000110011 (
b01101001 *
b111001101 -
#3
0#
#4
1#
b01101101 *
#5
0#
#6
1#
b01101010 *
#7
0#
#8
1#
b01101011 *
#9
0#
#10
1#
b01101101 *
#11
0#
#12
1#
b01101010 *
#13
0#
#14
1#
b01101100 *
#15
0#
#16
1#
b01101101 *
#17
0#
#18
1#
b01101100 *
#19
0#
#20
1#
b01110000 *
#21
0#
#22
1#
b01101001 *
#23
0#
#24
1#
b01101100 *
#25
0#
#26
1#
b01101110 *
#27
0#
#28
1#
b01101010 *
#29
0#
#30
1#
b01101111 *
#31
0#
#32
1#
b01100111 *
#33
0#
#34
1#
b01101011 *
#35
0#
#36
1#
b01101001 *
#37
0#
#38
1#
#39
0#
#40
1#
b01101010 *
#41
0#
#42
1#
b01101000 *
#43
0#
#44
1#
#45
0#
#46
1#
b01100110 *
#47
0#
#48
1#
b01100111 *
#49
0#
#50
1#
#51
0#
#52
1#
b01100000 *
#53
0#
#54
1#
b01100011 *
#55
0#
#56
1#
b01100100 *
#57
0#
#58
1#
b01101000 *
#59
0#
#60
1#
b01101001 *
#61
0#
#62
1#
b01100101 *
#63
0#
#64
1#
b01101010 *
#65
0#
#66
1#
b01100101 *
#67
0#
#68
1#
b01101010 *
#69
0#
#70
1#
b01101001 *
#71
0#
#72
1#
b01101000 *
#73
0#
#74
1#
b01101011 *
#75
0#
#76
1#
b01101001 *
#77
0#
#78
1#
b01101100 *
#79
0#
#80
1#
b01101000 *
#81
0#
#82
1#
b01101010 *
#83
0#
#84
1#
b01101101 *
#85
0#
#86
1#
b01101110 *
#87
0#
#88
1#
b01101100 *
#89
0#
#90
1#
b01101101 *
#91
0#
#92
1#
b01101010 *
#93
0#
#94
1#
b01101110 *
#95
0#
#96
1#
b01101000 *
#97
0#
#98
1#
b01101110 *
#99
0#
#100
1#
b01101001 *
#101
0#
#102
1#
b000110100 (
b01110000 *
b111001100 -
#103
0#
#104
1#
b01101111 *
#105
0#
#106
1#
b01101110 *
#107
0#
#108
1#
b000110101 (
b01101011 *
b111001011 -
#109
0#
#110
1#
b000110110 (
b01101111 *
b111001010 -
#111
0#
#112
1#
b000110111 (
b01101100 *
b111001001 -
#113
0#
#114
1#
b000111000 (
b01110010 *
b111001000 -
#115
0#
#116
1#
#117
0#
#118
1#
b01101101 *
#119
0#
#120
1#
b01110001 *
#121
0#
#122
1#
b01101110 *
#123
0#
#124
1#
b01110001 *
#125
0#
#126
1#
b01110101 *
#127
0#
#128
1#
b01110010 *
#129
0#
#130
1#
b01110011 *
#131
0#
#132
1#
b01110100 *
#133
0#
#134
1#
b01101111 *
#135
0#
#136
1#
b01110101 *
#137
0#
#138
1#
b01110110 *
#139
0#
#140
1#
b01110000 *
#141
0#
#142
1#
b01111000 *
#143
0#
#144
1#
b01110101 *
#145
0#
#146
1#
b000110111 (
b01110010 *
b111001001 -
#147
0#
#148
1#
b01110011 *
#149
0#
#150
1#
b000110110 (
b01110000 *
b111001010 -
#151
0#
#152
1#
b000110101 (
b01110001 *
b111001011 -
#153
0#
#154
1#
b000110100 (
b111001100 -
#155
0#
#156
1#
b000110011 (
b01101101 *
b111001101 -
#157
0#
#158
1#
#159
0#
#160
1#
b01101110 *
#161
0#
#162
1#
b01101011 *
#163
0#
#164
1#
b01101111 *
#165
0#
#166
1#
b01101011 *
#167
0#
#168
1#
b01101100 *
#169
0#
#170
1#
#171
0#
#172
1#
b01101110 *
#173
0#
#174
1#
b01101111 *
#175
0#
#176
1#
#177
0#
#178
1#
b01110001 *
#179
0#
#180
1#
b01110010 *
#181
0#
#182
1#
b01110001 *
#183
0#
#184
1#
b01110101 *
#185
0#
#186
1#
b01110000 *
#187
0#
#188
1#
b01110010 *
#189
0#
#190
1#
b01101100 *
#191
0#
#192
1#
b01110011 *
#193
0#
#194
1#
b01110010 *
#195
0#
#196
1#
b01110000 *
#197
0#
#198
1#
b000110010 (
b01110100 *
b111001110 -
#199
0#
#200
1#
b000110001 (
b01101100 *
b111001111 -
#201
0#
#202
1#
b000110000 (
b01101110 *
b111010000 -
#203
0#
#204
1#
b01101101 *
#205
0#
#206
1#
b01101111 *
#207
0#
#208
1#
b000101111 (
b01101101 *
b111010001 -
#209
0#
#210
1#
b01110001 *
#211
0#
#212
1#
b01101111 *
#213
0#
#214
1#
b01110010 *
#215
0#
#216
1#
b01101110 *
#217
0#
#218
1#
b01110001 *
#219
0#
#220
1#
b01101110 *
#221
0#
#222
1#
b01110010 *
#223
0#
#224
1#
#225
0#
#226
1#
b01110110 *
#227
0#
#228
1#
b01110100 *
#229
0#
#230
1#
b01110110 *
#231
0#
#232
1#
b01111000 *
#233
0#
#234
1#
b01111001 *
#235
0#
#236
1#
b000101110 (
b01111000 *
b111010010 -
#237
0#
#238
1#
b01110111 *
#239
0#
#240
1#
b01111000 *
#241
0#
#242
1#
b000101101 (
b01110100 *
b111010011 -
#243
0#
#244
1#
b01110010 *
#245
0#
#246
1#
b01101111 *
#247
0#
#248
1#
b01110001 *
#249
0#
#250
1#
b01101100 *
#251
0#
#252
1#
b01101110 *
#253
0#
#254
1#
b01101100 *
#255
0#
#256
1#
#257
0#
#258
1#
b01101001 *
#259
0#
#260
1#
b01110000 *
#261
0#
#262
1#
b01101100 *
#263
0#
#264
1#
b01101010 *
#265
0#
#266
1#
b01101001 *
#267
0#
#268
1#
b01101110 *
#269
0#
#270
1#
#271
0#
#272
1#
b01101100 *
#273
0#
#274
1#
b01110000 *
#275
0#
#276
1#
b01101100 *
#277
0#
#278
1#
b01110000 *
#279
0#
#280
1#
b01110011 *
#281
0#
#282
1#
b000101100 (
b01110001 *
b111010100 -
#283
0#
#284
1#
b000101011 (
b01101111 *
b111010101 -
#285
0#
#286
1#
b000101010 (
b01110101 *
b111010110 -
#287
0#
#288
1#
b000101001 (
b01110011 *
b111010111 -
#289
0#
#290
1#
b000101000 (
b111011000 -
#291
0#
#292
1#
b000100110 (
b111011010 -
#293
0#
#294
1#
b01110110 *
#295
0#
#296
1#
b01101111 *
#297
0#
#298
1#
b01110010 *
#299
0#
#300
1#
b01101111 *
#301
0#
#302
1#
b01101110 *
#303
0#
#304
1#
b01101100 *
#305
0#
#306
1#
b01101101 *
#307
0#
#308
1#
b01100110 *
#309
0#
#310
1#
b01101001 *
#311
0#
#312
1#
b01100111 *
#313
0#
#314
1#
b01100101 *
#315
0#
#316
1#
b01100100 *
#317
0#
#318
1#
b01100010 *
#319
0#
#320
1#
b01100101 *
#321
0#
#322
1#
b01100011 *
#323
0#
#324
1#
b01100000 *
#325
0#
#326
1#
b01100111 *
#327
0#
#328
1#
b01100100 *
#329
0#
#330
1#
b01100110 *
#331
0#
#332
1#
b01100111 *
#333
0#
#334
1#
b01101000 *
#335
0#
#336
1#
b01101011 *
#337
0#
#338
1#
b01101000 *
#339
0#
#340
1#
b01100110 *
#341
0#
#342
1#
b01101001 *
#343
0#
#344
1#
b01100111 *
#345
0#
#346
1#
b01110001 *
#347
0#
#348
1#
b01101010 *
#349
0#
#350
1#
b01101100 *
#351
0#
#352
1#
b01101101 *
#353
0#
#354
1#
b01101111 *
#355
0#
#356
1#
b01101010 *
#357
0#
#358
1#
b01110010 *
#359
0#
#360
1#
b000100101 (
b01101110 *
b111011011 -
#361
0#
#362
1#
b000100100 (
b01110000 *
b111011100 -
#363
0#
#364
1#
b000100011 (
b01101010 *
b111011101 -
#365
0#
#366
1#
b01110101 *
#367
0#
#368
1#
b01110000 *
#369
0#
#370
1#
b01101100 *
#371
0#
#372
1#
b01101111 *
#373
0#
#374
1#
b01101011 *
#375
0#
#376
1#
b01101100 *
#377
0#
#378
1#
b01101111 *
#379
0#
#380
1#
b01101101 *
#381
0#
#382
1#
b01101111 *
#383
0#
#384
1#
b01110000 *
#385
0#
#386
1#
b01101101 *
#387
0#
#388
1#
b01110000 *
#389
0#
#390
1#
b01101101 *
#391
0#
#392
1#
b01101111 *
#393
0#
#394
1#
b01101101 *
#395
0#
#396
1#
b01101010 *
#397
0#
#398
1#
b01101011 *
#399
0#
#400
1#
b01100111 *
#401
0#
#402
1#
b01101010 *
#403
0#
#404
1#
b01101000 *
#405
0#
#406
1#
b01101111 *
#407
0#
#408
1#
b01101000 *
#409
0#
#410
1#
b01100101 *
#411
0#
#412
1#
b01101000 *
#413
0#
#414
1#
b01011111 *
#415
0#
#416
1#
b01100001 *
#417
0#
#418
1#
#419
0#
#420
1#
#421
0#
#422
1#
b01100101 *
#423
0#
#424
1#
b01100111 *
#425
0#
#426
1#
b01100100 *
#427
0#
#428
1#
b000100001 (
b01100101 *
b111011111 -
#429
0#
#430
1#
b000100000 (
b01100100 *
b111100000 -
#431
0#
#432
1#
b000011111 (
b01101000 *
b111100001 -
#433
0#
#434
1#
b000011110 (
b01100000 *
b111100010 -
#435
0#
#436
1#
b000011100 (
b01101001 *
b111100100 -
#437
0#
#438
1#
b000011010 (
b01100101 *
b111100110 -
#439
0#
#440
1#
b01101001 *
#441
0#
#442
1#
#443
0#
#444
1#
b01101110 *
#445
0#
#446
1#
b01101101 *
#447
0#
#448
1#
b01101010 *
#449
0#
#450
1#
b01101101 *
#451
0#
#452
1#
#453
0#
#454
1#
#455
0#
#456
1#
b01101110 *
#457
0#
#458
1#
b01101001 *
#459
0#
#460
1#
b01101101 *
#461
0#
#462
1#
b01101011 *
#463
0#
#464
1#
b01101111 *
#465
0#
#466
1#
b01101011 *
#467
0#
#468
1#
b01101100 *
#469
0#
#470
1#
b01100110 *
#471
0#
#472
1#
b01101011 *
#473
0#
#474
1#
b01101101 *
#475
0#
#476
1#
#477
0#
#478
1#
b01101011 *
#479
0#
#480
1#
b000010110 (
b01101100 *
b111101010 -
#481
0#
#482
1#
b000010100 (
b01101110 *
b111101100 -
#483
0#
#484
1#
b000010001 (
b01110001 *
b111101111 -
#485
0#
#486
1#
#487
0#
#488
1#
b01101110 *
#489
0#
#490
1#
b01110100 *
#491
0#
#492
1#
b01110001 *
#493
0#
#494
1#
b01110011 *
#495
0#
#496
1#
b01110000 *
#497
0#
#498
1#
b01110101 *
#499
0#
#500
1#
b01110010 *
#501
0#
#502
1#
b01110000 *
#503
0#
#504
1#
#505
0#
#506
1#
b01110010 *
#507
0#
#508
1#
b000001111 (
b01101100 *
b111110001 -
#509
0#
#510
1#
b000001101 (
b01101011 *
b111110011 -
#511
0#
#512
1#
b000001100 (
b111110100 -
#513
0#
#514
1#
b000001011 (
b01110000 *
b111110101 -
#515
0#
#516
1#
b01101001 *
#517
0#
#518
1#
b01101010 *
#519
0#
#520
1#
b01110000 *
#521
0#
#522
1#
b01101111 *
#523
0#
#524
1#
b01101101 *
#525
0#
#526
1#
b01110001 *
#527
0#
#528
1#
b01101010 *
#529
0#
#530
1#
b01110001 *
#531
0#
#532
1#
b01101100 *
#533
0#
#534
1#
b01110001 *
#535
0#
#536
1#
b01110010 *
#537
0#
#538
1#
b000001010 (
b01110101 *
b111110110 -
#539
0#
#540
1#
b000001001 (
b01110100 *
b111110111 -
#541
0#
#542
1#
b000001000 (
b111111000 -
#543
0#
#544
1#
b000000110 (
b01110101 *
b111111010 -
#545
0#
#546
1#
b000000101 (
b01110111 *
b111111011 -
#547
0#
#548
1#
b01110100 *
#549
0#
#550
1#
b000000100 (
b01110101 *
b111111100 -
#551
0#
#552
1#
b01110110 *
#553
0#
#554
1#
b01110010 *
#555
0#
#556
1#
b01110101 *
#557
0#
#558
1#
b01101100 *
#559
0#
#560
1#
b01110010 *
#561
0#
#562
1#
b01110001 *
#563
0#
#564
1#
b01101001 *
#565
0#
#566
1#
b01101011 *
#567
0#
#568
1#
b01110000 *
#569
0#
#570
1#
b01101000 *
#571
0#
#572
1#
b01101100 *
#573
0#
#574
1#
b01101000 *
#575
0#
#576
1#
b000000011 (
b01101011 *
b111111101 -
#577
0#
#578
1#
b01101100 *
#579
0#
#580
1#
b01101011 *
#581
0#
#582
1#
b000000010 (
b01101100 *
b111111110 -
#583
0#
#584
1#
b000000001 (
b111111111 -
#585
0#
#586
1#
b000000000 (
b01101010 *
b000000000 -
#587
0#
#588
1#
b01101111 *
b01101100 +
#589
0#
#590
1#
b01110000 *
b01101010 +
#591
0#
#592
1#
b01101111 *
b01101111 +
#593
0#
#594
1#
b01110000 *
b01110000 +
#595
0#
#596
1#
b01101100 *
b01101111 +
#597
0#
#598
1#
b01101110 *
b01110000 +
#599
0#
#600
1#
b01110010 *
b01101100 +
#601
0#
#602
1#
b01110011 *
b01101110 +
#603
0#
#604
1#
b01110010 *
b01110010 +
#605
0#
#606
1#
b01110011 *
b01110011 +
#607
0#
#608
1#
b01111001 *
b01110010 +
#609
0#
#610
1#
b01111000 *
b01110011 +
#611
0#
#612
1#
b01110100 *
b01111001 +
#613
0#
#614
1#
b000000001 (
b01111000 *
b01111000 +
b111111111 -
#615
0#
#616
1#
b00000000 +
#617
0#
#618
1#
#619
0#
#620
1#
b01111010 *
#621
0#
#622
1#
b01110011 *
#623
0#
#624
1#
b01110100 *
#625
0#
#626
1#
b01110000 *
#627
0#
#628
1#
b01110011 *
#629
0#
#630
1#
b01110101 *
#631
0#
#632
1#
b01110010 *
#633
0#
#634
1#
b01111000 *
#635
0#
#636
1#
b01110100 *
#637
0#
#638
1#
b01110101 *
#639
0#
#640
1#
b01110001 *
#641
0#
#642
1#
b01110011 *
#643
0#
#644
1#
b01110100 *
#645
0#
#646
1#
b01110010 *
#647
0#
#648
1#
b01110001 *
#649
0#
#650
1#
b01110101 *
#651
0#
#652
1#
b01110011 *
#653
0#
#654
1#
b01110010 *
#655
0#
#656
1#
b01110001 *
#657
0#
#658
1#
b01101111 *
#659
0#
#660
1#
b01101110 *
#661
0#
#662
1#
b01101011 *
#663
0#
#664
1#
b01101110 *
#665
0#
#666
1#
b01101111 *
#667
0#
#668
1#
b01101100 *
#669
0#
#670
1#
b01101000 *
#671
0#
#672
1#
b000000000 (
b01101001 *
b000000000 -
#673
0#
#674
1#
b01101010 *
b01101000 +
#675
0#
#676
1#
b01101011 *
b01101001 +
#677
0#
#678
1#
b01101000 *
b01101010 +
#679
0#
#680
1#
b01101010 *
b01101011 +
#681
0#
#682
1#
b01101011 *
b01101000 +
#683
0#
#684
1#
b01100110 *
b01101010 +
#685
0#
#686
1#
b01101011 *
b01101011 +
#687
0#
#688
1#
b01101100 *
b01100110 +
#689
0#
#690
1#
b01101011 *
b01101011 +
#691
0#
#692
1#
b01101000 *
b01101100 +
#693
0#
#694
1#
b01101100 *
b01101011 +
#695
0#
#696
1#
b01101000 +
#697
0#
#698
1#
b01101100 +
#699
0#
#700
1#
b01101011 *
#701
0#
#702
1#
#703
0#
#704
1#
b000000001 (
b01101001 *
b01101011 +
b111111111 -
#705
0#
#706
1#
b01101011 *
b00000000 +
#707
0#
#708
1#
b01101100 *
#709
0#
#710
1#
b01101110 *
#711
0#
#712
1#
b01101001 *
#713
0#
#714
1#
b01101110 *
#715
0#
#716
1#
b01101100 *
#717
0#
#718
1#
b01101010 *
#719
0#
#720
1#
b01101011 *
#721
0#
#722
1#
b01101010 *
#723
0#
#724
1#
#725
0#
#726
1#
b01101100 *
#727
0#
#728
1#
#729
0#
#730
1#
#731
0#
#732
1#
b01101001 *
#733
0#
#734
1#
b01101110 *
#735
0#
#736
1#
b01101100 *
#737
0#
#738
1#
#739
0#
#740
1#
#741
0#
#742
1#
b01101110 *
#743
0#
#744
1#
b01101100 *
#745
0#
#746
1#
b01101110 *
#747
0#
#748
1#
b01110010 *
#749
0#
#750
1#
b01101100 *
#751
0#
#752
1#
b01110000 *
#753
0#
#754
1#
b01101101 *
#755
0#
#756
1#
b01101100 *
#757
0#
#758
1#
b01110000 *
#759
0#
#760
1#
b01101101 *
#761
0#
#762
1#
b01110010 *
#763
0#
#764
1#
b01101100 *
#765
0#
#766
1#
b01101101 *
#767
0#
#768
1#
b01100111 *
#769
0#
#770
1#
b01101111 *
#771
0#
#772
1#
b01100111 *
#773
0#
#774
1#
b01101000 *
#775
0#
#776
1#
b01101011 *
#777
0#
#778
1#
b01101111 *
#779
0#
#780
1#
b01101001 *
#781
0#
#782
1#
b01101010 *
#783
0#
#784
1#
b01101101 *
#785
0#
#786
1#
b01101011 *
#787
0#
#788
1#
#789
0#
#790
1#
b01101001 *
#791
0#
#792
1#
b01101101 *
#793
0#
#794
1#
b01101110 *
#795
0#
#796
1#
#797
0#
#798
1#
b01101101 *
#799
0#
#800
1#
b01101111 *
#801
0#
#802
1#
b01101000 *
#803
0#
#804
1#
b01101011 *
#805
0#
#806
1#
b01101100 *
#807
0#
#808
1#
b01101010 *
#809
0#
#810
1#
#811
0#
#812
1#
b01100101 *
#813
0#
#814
1#
b01101001 *
#815
0#
#816
1#
b01101101 *
#817
0#
#818
1#
b01101000 *
#819
0#
#820
1#
b01100110 *
#821
0#
#822
1#
b01100111 *
#823
0#
#824
1#
b01100101 *
#825
0#
#826
1#
b01101000 *
#827
0#
#828
1#
b01100101 *
#829
0#
#830
1#
b01101011 *
#831
0#
#832
1#
b01100011 *
#833
0#
#834
1#
b01100110 *
#835
0#
#836
1#
b01101000 *
#837
0#
#838
1#
b01101001 *
#839
0#
#840
1#
b01100011 *
#841
0#
#842
1#
b01100101 *
#843
0#
#844
1#
b01101001 *
#845
0#
#846
1#
b01100111 *
#847
0#
#848
1#
b01101001 *
#849
0#
#850
1#
b01101100 *
#851
0#
#852
1#
b01101010 *
#853
0#
#854
1#
b01101111 *
#855
0#
#856
1#
#857
0#
#858
1#
b01101101 *
#859
0#
#860
1#
#861
0#
#862
1#
#863
0#
#864
1#
#865
0#
#866
1#
#867
0#
#868
1#
#869
0#
#870
1#
#871
0#
#872
1#
b01101111 *
#873
0#
#874
1#
b01101110 *
#875
0#
#876
1#
b01101100 *
#877
0#
#878
1#
b01110001 *
#879
0#
#880
1#
b01101010 *
#881
0#
#882
1#
b01101101 *
#883
0#
#884
1#
b01101110 *
#885
0#
#886
1#
b01101101 *
#887
0#
#888
1#
#889
0#
#890
1#
#891
0#
#892
1#
#893
0#
#894
1#
b01101100 *
#895
0#
#896
1#
b01101101 *
#897
0#
#898
1#
b01110000 *
#899
0#
#900
1#
b01101011 *
#901
0#
#902
1#
b01101101 *
#903
0#
#904
1#
b01101110 *
#905
0#
#906
1#
b01110011 *
#907
0#
#908
1#
b01110000 *
#909
0#
#910
1#
b01110001 *
#911
0#
#912
1#
#913
0#
#914
1#
b01110101 *
#915
0#
#916
1#
b01110100 *
#917
0#
#918
1#
b01110010 *
#919
0#
#920
1#
#921
0#
#922
1#
b01101110 *
#923
0#
#924
1#
b01110100 *
#925
0#
#926
1#
b01101111 *
#927
0#
#928
1#
b01110010 *
#929
0#
#930
1#
b01110000 *
#931
0#
#932
1#
b01101111 *
#933
0#
#934
1#
b01110000 *
#935
0#
#936
1#
b01110001 *
#937
0#
#938
1#
b01110000 *
#939
0#
#940
1#
b01101100 *
#941
0#
#942
1#
b01101110 *
#943
0#
#944
1#
#945
0#
#946
1#
b01101101 *
#947
0#
#948
1#
b01101011 *
#949
0#
#950
1#
b01110000 *
#951
0#
#952
1#
b01101101 *
#953
0#
#954
1#
b01110001 *
#955
0#
#956
1#
b01101110 *
#957
0#
#958
1#
b01110000 *
#959
0#
#960
1#
b01110001 *
#961
0#
#962
1#
b01110011 *
#963
0#
#964
1#
#965
0#
#966
1#
b01110010 *
#967
0#
#968
1#
b01110001 *
#969
0#
#970
1#
b01110010 *
#971
0#
#972
1#
b01110001 *
#973
0#
#974
1#
b01110010 *
#975
0#
#976
1#
#977
0#
#978
1#
#979
0#
#980
1#
b01101111 *
#981
0#
#982
1#
b01110000 *
#983
0#
#984
1#
b01101110 *
#985
0#
#986
1#
b01101101 *
#987
0#
#988
1#
b01101111 *
#989
0#
#990
1#
b01101010 *
#991
0#
#992
1#
b01101111 *
#993
0#
#994
1#
b01101011 *
#995
0#
#996
1#
b01101101 *
#997
0#
#998
1#
b01101111 *
#999
0#
#1000
1#
#1001
0#
#1002
1#
b01110100 *
#1003
0#
#1004
1#
b01101111 *
#1005
0#
#1006
1#
b01110100 *
#1007
0#
#1008
1#
b01110010 *
#1009
0#
#1010
1#
b01101111 *
#1011
0#
#1012
1#
b01110100 *
#1013
0#
#1014
1#
b01110110 *
#1015
0#
#1016
1#
b01111011 *
#1017
0#
#1018
1#
b01111001 *
#1019
0#
#1020
1#
b01111000 *
#1021
0#
#1022
1#
b10000000 *
#1023
0#
#1024
1#
b01111100 *
#1025
0#
#1026
1#
b01110001 *
#1027
0#
#1028
1#
b01110011 *
#1029
0#
#1030
1#
b01110100 *
#1031
0#
#1032
1#
b01101110 *
#1033
0#
#1034
1#
b01110001 *
#1035
0#
#1036
1#
b01101100 *
#1037
0#
#1038
1#
b01101011 *
#1039
0#
#1040
1#
b01101100 *
#1041
0#
#1042
1#
b01101101 *
#1043
0#
#1044
1#
b01101011 *
#1045
0#
#1046
1#
b01101001 *
#1047
0#
#1048
1#
b01101010 *
#1049
0#
#1050
1#
b01100111 *
#1051
0#
#1052
1#
b01100101 *
#1053
0#
#1054
1#
b01101010 *
#1055
0#
#1056
1#
b01101000 *
#1057
0#
#1058
1#
#1059
0#
#1060
1#
b01101011 *
#1061
0#
#1062
1#
b01101010 *
#1063
0#
#1064
1#
b01101001 *
#1065
0#
#1066
1#
b01101010 *
#1067
0#
#1068
1#
b01100110 *
#1069
0#
#1070
1#
b01100111 *
#1071
0#
#1072
1#
b01101001 *
#1073
0#
#1074
1#
b01100101 *
#1075
0#
#1076
1#
b01101000 *
#1077
0#
#1078
1#
b01100111 *
#1079
0#
#1080
1#
b01101000 *
#1081
0#
#1082
1#
#1083
0#
#1084
1#
b01101011 *
#1085
0#
#1086
1#
b01101100 *
#1087
0#
#1088
1#
b01100111 *
#1089
0#
#1090
1#
b01110001 *
#1091
0#
#1092
1#
b01101110 *
#1093
0#
#1094
1#
b01110000 *
#1095
0#
#1096
1#
b01110001 *
#1097
0#
#1098
1#
b01110000 *
#1099
0#
#1100
1#
b01101100 *
#1101
0#
#1102
1#
b01110001 *
#1103
0#
#1104
1#
b01101011 *
#1105
0#
#1106
1#
b01101110 *
#1107
0#
#1108
1#
b01101101 *
#1109
0#
#1110
1#
b01110000 *
#1111
0#
#1112
1#
b01101100 *
#1113
0#
#1114
1#
b01101011 *
#1115
0#
#1116
1#
#1117
0#
#1118
1#
b01101101 *
#1119
0#
#1120
1#
b01101110 *
#1121
0#
#1122
1#
b01101011 *
#1123
0#
#1124
1#
b01101100 *
#1125
0#
#1126
1#
b01110000 *
#1127
0#
#1128
1#
b01101110 *
#1129
0#
#1130
1#
b01101111 *
#1131
0#
#1132
1#
b01110010 *
#1133
0#
#1134
1#
b01110101 *
#1135
0#
#1136
1#
b01110100 *
#1137
0#
#1138
1#
b01110111 *
#1139
0#
#1140
1#
#1141
0#
#1142
1#
b01111001 *
#1143
0#
#1144
1#
b01111010 *
#1145
0#
#1146
1#
b01111001 *
#1147
0#
#1148
1#
b01110110 *
#1149
0#
#1150
1#
b01111000 *
#1151
0#
#1152
1#
b01110000 *
#1153
0#
#1154
1#
b01110011 *
#1155
0#
#1156
1#
b01110001 *
#1157
0#
#1158
1#
b01101100 *
#1159
0#
#1160
1#
b01101110 *
#1161
0#
#1162
1#
#1163
0#
#1164
1#
b01101010 *
#1165
0#
#1166
1#
b01101101 *
#1167
0#
#1168
1#
b01101011 *
#1169
0#
#1170
1#
b01101101 *
#1171
0#
#1172
1#
b01101010 *
#1173
0#
#1174
1#
b01101110 *
#1175
0#
#1176
1#
b01101001 *
#1177
0#
#1178
1#
b01101011 *
#1179
0#
#1180
1#
b01101001 *
#1181
0#
#1182
1#
b01100111 *
#1183
0#
#1184
1#
b01101101 *
#1185
0#
#1186
1#
b01101011 *
#1187
0#
#1188
1#
b01101000 *
#1189
0#
#1190
1#
b01101101 *
#1191
0#
#1192
1#
b01101001 *
#1193
0#
#1194
1#
b01101100 *
#1195
0#
#1196
1#
#1197
0#
#1198
1#
b01101010 *
#1199
0#
#1200
1#
#1201
0#
#1202
1#
b01101011 *
#1203
0#
#1204
1#
b01101010 *
#1205
0#
#1206
1#
b01101101 *
#1207
0#
#1208
1#
b01101100 *
#1209
0#
#1210
1#
b01101111 *
#1211
0#
#1212
1#
b01101101 *
#1213
0#
#1214
1#
b01110001 *
#1215
0#
#1216
1#
b01110011 *
#1217
0#
#1218
1#
b01101111 *
#1219
0#
#1220
1#
#1221
0#
#1222
1#
b01110001 *
#1223
0#
#1224
1#
b01101111 *
#1225
0#
#1226
1#
b01101100 *
#1227
0#
#1228
1#
b01110000 *
#1229
0#
#1230
1#
b01101101 *
#1231
0#
#1232
1#
#1233
0#
#1234
1#
b01101110 *
#1235
0#
#1236
1#
b01101011 *
#1237
0#
#1238
1#
b01101100 *
#1239
0#
#1240
1#
b01101011 *
#1241
0#
#1242
1#
b01101001 *
#1243
0#
#1244
1#
b01101010 *
#1245
0#
#1246
1#
b01101100 *
#1247
0#
#1248
1#
b01101010 *
#1249
0#
#1250
1#
b01101101 *
#1251
0#
#1252
1#
b01101110 *
#1253
0#
#1254
1#
b01110000 *
#1255
0#
#1256
1#
b01110001 *
#1257
0#
#1258
1#
#1259
0#
#1260
1#
b01110011 *
#1261
0#
#1262
1#
#1263
0#
#1264
1#
b01110010 *
#1265
0#
#1266
1#
b01110100 *
#1267
0#
#1268
1#
b01110011 *
#1269
0#
#1270
1#
#1271
0#
#1272
1#
b01110100 *
#1273
0#
#1274
1#
b01110010 *
#1275
0#
#1276
1#
b01110001 *
#1277
0#
#1278
1#
b01110010 *
#1279
0#
#1280
1#
b01110000 *
#1281
0#
#1282
1#
b01110001 *
#1283
0#
#1284
1#
b01110000 *
#1285
0#
#1286
1#
b01110010 *
#1287
0#
#1288
1#
#1289
0#
#1290
1#
b01110001 *
#1291
0#
#1292
1#
b01110010 *
#1293
0#
#1294
1#
#1295
0#
#1296
1#
#1297
0#
#1298
1#
b01110011 *
#1299
0#
#1300
1#
b01110000 *
#1301
0#
#1302
1#
b01101111 *
#1303
0#
#1304
1#
b01110000 *
#1305
0#
#1306
1#
b01101110 *
#1307
0#
